gcloudtail.py
gcloud_tail-1.0.0.dist-info/METADATA
gcloud_tail-1.0.0.dist-info/WHEEL
gcloud_tail-1.0.0.dist-info/entry_points.txt
gcloud_tail-1.0.0.dist-info/top_level.txt
gcloud_tail-1.0.0.dist-info/RECORD
